<mockup version="4.2" platform="MtMobile" defaultW="360" defaultH="640" from="FmLocal" screenOrientation="MoPortrait" mobileScreenScale="1.77777779102325" ID="00D36436-4F6C-477E-B691-9680E3A3DE10" measureW="360" measureH="640" clipArea="(0,0,0,0)" minAllowVersion="4.1">
  <controls controlCount="13">
    <control controlID="31DC402A-B56C-42DC-BC01-F0A451A755E2" controlTypeID="Shape" isShow="True" caption="%E5%BD%A2%E7%8A%B6" x="0" y="0" w="360" h="50" measuredW="120" measuredH="100" zOrder="0" locked="False" sizeLocked="False">
      <controlProperties>
        <basic color="4294967295" borderVisible="False" borderColor="4282664004" isAutoSize="False" status="MsEnabled" opacity="1" isCommentCom="False" canMove="True" alias="" rotation="0"/>
        <states/>
        <verticalScrollbarShow>False</verticalScrollbarShow>
        <verticalScrollbarProgress>30</verticalScrollbarProgress>
        <horizontalScrollbarShow>False</horizontalScrollbarShow>
        <horizontalScrollbarProgress>30</horizontalScrollbarProgress>
        <links eventType="AtClick" animate="AmNone" animateAutoDelay="0" animateDuration="500">
          <link targetPageID="" linkType="ltPageLink" isApplyIncludePage="False" title="%E9%93%BE%E6%8E%A5">
            <area shape="0" alt="" ID="{B5CEF6FA-CEE8-4459-834C-810BE2D1C614}" coords="(0,0,360,50)"/>
          </link>
        </links>
        <interactiveData>
          <entry title="">
            <area shape="0" alt="" ID="{64A4CA94-417C-4AD0-BFF3-25758FF0B00F}" coords="(0,0,360,50)"/>
            <events title=""/>
          </entry>
        </interactiveData>
        <textSet textColor="4278190080" textSize="16" textFontFamily="%E5%BE%AE%E8%BD%AF%E9%9B%85%E9%BB%91" lineSpacingMultiple="1" textAlign="HaCenter" textVAlign="VaMiddle" textWordWrap="True" textStyles="[]" useDefaultTextSize="False">
          <text>%E6%88%91%E8%A6%81%E8%AE%B2%E8%BF%B0</text>
        </textSet>
        <selectedIndex>-1</selectedIndex>
        <selectedColor>4282501083</selectedColor>
        <textPadding>0</textPadding>
        <shapeBorderType>SbRectangle</shapeBorderType>
        <triangleType>TdZero</triangleType>
        <dashMode>SdSolid</dashMode>
        <rectangleBorderLeftVisible>True</rectangleBorderLeftVisible>
        <rectangleBorderRightVisible>True</rectangleBorderRightVisible>
        <rectangleBorderTopVisible>True</rectangleBorderTopVisible>
        <rectangleBorderBottomVisible>True</rectangleBorderBottomVisible>
        <radius>0</radius>
        <radiusIsPercent>True</radiusIsPercent>
        <thickness>1</thickness>
      </controlProperties>
    </control>
    <control controlID="28EF4F56-0005-41EB-AFC8-E67181E8EFB4" controlTypeID="Icon" isShow="True" caption="%E5%9B%BE%E6%A0%87" x="6" y="13" w="24" h="24" measuredW="32" measuredH="32" zOrder="1" locked="False" sizeLocked="False">
      <controlProperties>
        <basic color="4282664004" borderVisible="True" borderColor="0" isAutoSize="False" status="MsEnabled" opacity="1" isCommentCom="False" canMove="True" alias="" rotation="0"/>
        <states/>
        <verticalScrollbarShow>False</verticalScrollbarShow>
        <verticalScrollbarProgress>30</verticalScrollbarProgress>
        <horizontalScrollbarShow>False</horizontalScrollbarShow>
        <horizontalScrollbarProgress>30</horizontalScrollbarProgress>
        <links eventType="AtClick" animate="AmNone" animateAutoDelay="0" animateDuration="200">
          <link targetPageID="18B81922-567F-47E2-9637-F4E661867BD0" linkType="ltPageLink" isApplyIncludePage="False" title="%E8%AE%B2%E8%BF%B0%E5%BC%B9%E7%AA%97">
            <area shape="0" alt="" ID="{6384F599-DC62-4940-A38C-2D45DF1B3661}" coords="(0,0,24,24)"/>
          </link>
        </links>
        <interactiveData>
          <entry title="">
            <area shape="0" alt="" ID="{13741FCC-9D7A-4208-8098-DC93B27A6F6D}" coords="(0,0,24,24)"/>
            <events title=""/>
          </entry>
        </interactiveData>
        <rotationAngle>TdZero</rotationAngle>
        <icon>
          <ID>Back.png</ID>
          <iconFontName/>
          <iconCode>-1</iconCode>
        </icon>
        <URL/>
        <FlipHorizontal>False</FlipHorizontal>
        <FlipVertical>False</FlipVertical>
      </controlProperties>
    </control>
    <control controlID="7E9C1651-BD24-45A4-A908-D55E3C7E29AD" controlTypeID="Shape" isShow="True" caption="%E5%BD%A2%E7%8A%B6" x="0" y="57" w="360" h="583" measuredW="120" measuredH="100" zOrder="2" locked="False" sizeLocked="False">
      <controlProperties>
        <basic color="4292335575" borderVisible="False" borderColor="4282664004" isAutoSize="False" status="MsEnabled" opacity="1" isCommentCom="False" canMove="True" alias="" rotation="0"/>
        <states/>
        <verticalScrollbarShow>False</verticalScrollbarShow>
        <verticalScrollbarProgress>30</verticalScrollbarProgress>
        <horizontalScrollbarShow>False</horizontalScrollbarShow>
        <horizontalScrollbarProgress>30</horizontalScrollbarProgress>
        <links eventType="AtClick" animate="AmPushDown" animateAutoDelay="0" animateDuration="500">
          <link targetPageID="" linkType="ltPageLink" isApplyIncludePage="False" title="%E9%93%BE%E6%8E%A5">
            <area shape="0" alt="" ID="{113BBED9-53B9-41C2-8D07-A42EFDC39EF5}" coords="(0,0,360,583)"/>
          </link>
        </links>
        <interactiveData>
          <entry title="">
            <area shape="0" alt="" ID="{722852B3-E9B0-4C0C-8DAF-FD4B2591C522}" coords="(0,0,360,583)"/>
            <events title=""/>
          </entry>
        </interactiveData>
        <textSet textColor="4278190080" textSize="14" textFontFamily="%E5%BE%AE%E8%BD%AF%E9%9B%85%E9%BB%91" lineSpacingMultiple="1" textAlign="HaCenter" textVAlign="VaMiddle" textWordWrap="True" textStyles="[]" useDefaultTextSize="True"/>
        <selectedIndex>-1</selectedIndex>
        <selectedColor>4282501083</selectedColor>
        <textPadding>0</textPadding>
        <shapeBorderType>SbRectangle</shapeBorderType>
        <triangleType>TdZero</triangleType>
        <dashMode>SdSolid</dashMode>
        <rectangleBorderLeftVisible>True</rectangleBorderLeftVisible>
        <rectangleBorderRightVisible>True</rectangleBorderRightVisible>
        <rectangleBorderTopVisible>True</rectangleBorderTopVisible>
        <rectangleBorderBottomVisible>True</rectangleBorderBottomVisible>
        <radius>0</radius>
        <radiusIsPercent>True</radiusIsPercent>
        <thickness>1</thickness>
      </controlProperties>
    </control>
    <control controlID="03F07235-C9CB-4893-8FDB-BCC2BB98B2C6" controlTypeID="Shape" isShow="True" caption="%E5%BD%A2%E7%8A%B6" x="0" y="57" w="360" h="69" measuredW="120" measuredH="100" zOrder="3" locked="False" sizeLocked="False">
      <controlProperties>
        <basic color="4294111986" borderVisible="False" borderColor="4282664004" isAutoSize="False" status="MsEnabled" opacity="1" isCommentCom="False" canMove="True" alias="" rotation="0"/>
        <states/>
        <verticalScrollbarShow>False</verticalScrollbarShow>
        <verticalScrollbarProgress>30</verticalScrollbarProgress>
        <horizontalScrollbarShow>False</horizontalScrollbarShow>
        <horizontalScrollbarProgress>30</horizontalScrollbarProgress>
        <links eventType="AtClick" animate="AmPushRight" animateAutoDelay="0" animateDuration="500">
          <link targetPageID="" linkType="ltPageLink" isApplyIncludePage="False" title="%E9%93%BE%E6%8E%A5">
            <area shape="0" alt="" ID="{0B9410B6-BDE9-41BF-9093-48FB17DC19C8}" coords="(0,0,360,69)"/>
          </link>
        </links>
        <interactiveData>
          <entry title="">
            <area shape="0" alt="" ID="{74E2CBC9-E273-45D0-8AB0-1A4F02DD51BD}" coords="(0,0,360,69)"/>
            <events title=""/>
          </entry>
        </interactiveData>
        <textSet textColor="4278190080" textSize="14" textFontFamily="%E5%BE%AE%E8%BD%AF%E9%9B%85%E9%BB%91" lineSpacingMultiple="1" textAlign="HaCenter" textVAlign="VaMiddle" textWordWrap="True" textStyles="[]" useDefaultTextSize="True"/>
        <selectedIndex>-1</selectedIndex>
        <selectedColor>4282501083</selectedColor>
        <textPadding>0</textPadding>
        <shapeBorderType>SbRectangle</shapeBorderType>
        <triangleType>TdZero</triangleType>
        <dashMode>SdSolid</dashMode>
        <rectangleBorderLeftVisible>True</rectangleBorderLeftVisible>
        <rectangleBorderRightVisible>True</rectangleBorderRightVisible>
        <rectangleBorderTopVisible>True</rectangleBorderTopVisible>
        <rectangleBorderBottomVisible>True</rectangleBorderBottomVisible>
        <radius>0</radius>
        <radiusIsPercent>True</radiusIsPercent>
        <thickness>1</thickness>
      </controlProperties>
    </control>
    <control controlID="C0304944-B860-4C34-B9C5-4812CA098A5A" controlTypeID="Label" isShow="True" caption="%E5%8D%95%E8%A1%8C%E6%96%87%E5%AD%97" x="8" y="81" w="96" h="22" measuredW="0" measuredH="0" zOrder="4" locked="False" sizeLocked="False">
      <controlProperties>
        <basic color="16777215" borderVisible="True" borderColor="0" isAutoSize="True" status="MsEnabled" opacity="1" isCommentCom="False" canMove="True" alias="" rotation="0"/>
        <states/>
        <verticalScrollbarShow>False</verticalScrollbarShow>
        <verticalScrollbarProgress>30</verticalScrollbarProgress>
        <horizontalScrollbarShow>False</horizontalScrollbarShow>
        <horizontalScrollbarProgress>30</horizontalScrollbarProgress>
        <links eventType="AtClick" animate="AmPushRight" animateAutoDelay="0" animateDuration="500">
          <link targetPageID="" linkType="ltPageLink" isApplyIncludePage="False" title="%E9%93%BE%E6%8E%A5">
            <area shape="0" alt="" ID="{70C61E3A-5482-4E91-B25E-E689AFBE9559}" coords="(0,0,96,22)"/>
          </link>
        </links>
        <interactiveData>
          <entry title="">
            <area shape="0" alt="" ID="{902C6714-C6AC-4948-9D95-EF097DC4B6AE}" coords="(0,0,96,22)"/>
            <events title=""/>
          </entry>
        </interactiveData>
        <textSet textColor="4289638062" textSize="16" textFontFamily="%E5%BE%AE%E8%BD%AF%E9%9B%85%E9%BB%91" lineSpacingMultiple="1" textAlign="HaLeft" textVAlign="VaTop" textWordWrap="True" textStyles="[]" useDefaultTextSize="False">
          <text>%E7%82%B9%E5%87%BB%E8%BE%93%E5%85%A5%E6%A0%87%E9%A2%98</text>
        </textSet>
        <selectedIndex>-1</selectedIndex>
        <selectedColor>4282501083</selectedColor>
        <textPadding>0</textPadding>
      </controlProperties>
    </control>
    <control controlID="C03E8662-DB6F-4598-9998-1D2970550846" controlTypeID="Shape" isShow="True" caption="%E5%BD%A2%E7%8A%B6" x="0" y="586" w="360" h="60" measuredW="120" measuredH="100" zOrder="5" locked="False" sizeLocked="False">
      <controlProperties>
        <basic color="4293190884" borderVisible="False" borderColor="4282664004" isAutoSize="False" status="MsEnabled" opacity="1" isCommentCom="False" canMove="True" alias="" rotation="0"/>
        <states/>
        <verticalScrollbarShow>False</verticalScrollbarShow>
        <verticalScrollbarProgress>30</verticalScrollbarProgress>
        <horizontalScrollbarShow>False</horizontalScrollbarShow>
        <horizontalScrollbarProgress>30</horizontalScrollbarProgress>
        <links eventType="AtClick" animate="AmPushRight" animateAutoDelay="0" animateDuration="500">
          <link targetPageID="" linkType="ltPageLink" isApplyIncludePage="False" title="%E9%93%BE%E6%8E%A5">
            <area shape="0" alt="" ID="{0B9410B6-BDE9-41BF-9093-48FB17DC19C8}" coords="(0,0,360,60)"/>
          </link>
        </links>
        <interactiveData>
          <entry title="">
            <area shape="0" alt="" ID="{74E2CBC9-E273-45D0-8AB0-1A4F02DD51BD}" coords="(0,0,360,60)"/>
            <events title=""/>
          </entry>
        </interactiveData>
        <textSet textColor="4278190080" textSize="14" textFontFamily="%E5%BE%AE%E8%BD%AF%E9%9B%85%E9%BB%91" lineSpacingMultiple="1" textAlign="HaCenter" textVAlign="VaMiddle" textWordWrap="True" textStyles="[]" useDefaultTextSize="True"/>
        <selectedIndex>-1</selectedIndex>
        <selectedColor>4282501083</selectedColor>
        <textPadding>0</textPadding>
        <shapeBorderType>SbRectangle</shapeBorderType>
        <triangleType>TdZero</triangleType>
        <dashMode>SdSolid</dashMode>
        <rectangleBorderLeftVisible>True</rectangleBorderLeftVisible>
        <rectangleBorderRightVisible>True</rectangleBorderRightVisible>
        <rectangleBorderTopVisible>True</rectangleBorderTopVisible>
        <rectangleBorderBottomVisible>True</rectangleBorderBottomVisible>
        <radius>0</radius>
        <radiusIsPercent>True</radiusIsPercent>
        <thickness>1</thickness>
      </controlProperties>
    </control>
    <control controlID="B0574918-0E8A-4991-A255-F4FDE2896906" controlTypeID="Label" isShow="True" caption="%E5%8D%95%E8%A1%8C%E6%96%87%E5%AD%97" x="8" y="146" w="168" h="19" measuredW="0" measuredH="0" zOrder="6" locked="False" sizeLocked="False">
      <controlProperties>
        <basic color="16777215" borderVisible="True" borderColor="0" isAutoSize="True" status="MsEnabled" opacity="1" isCommentCom="False" canMove="True" alias="" rotation="0"/>
        <states/>
        <verticalScrollbarShow>False</verticalScrollbarShow>
        <verticalScrollbarProgress>30</verticalScrollbarProgress>
        <horizontalScrollbarShow>False</horizontalScrollbarShow>
        <horizontalScrollbarProgress>30</horizontalScrollbarProgress>
        <links eventType="AtClick" animate="AmPushRight" animateAutoDelay="0" animateDuration="500">
          <link targetPageID="" linkType="ltPageLink" isApplyIncludePage="False" title="%E9%93%BE%E6%8E%A5">
            <area shape="0" alt="" ID="{70C61E3A-5482-4E91-B25E-E689AFBE9559}" coords="(0,0,168,19)"/>
          </link>
        </links>
        <interactiveData>
          <entry title="">
            <area shape="0" alt="" ID="{902C6714-C6AC-4948-9D95-EF097DC4B6AE}" coords="(0,0,168,19)"/>
            <events title=""/>
          </entry>
        </interactiveData>
        <textSet textColor="4289638062" textSize="14" textFontFamily="%E5%BE%AE%E8%BD%AF%E9%9B%85%E9%BB%91" lineSpacingMultiple="1" textAlign="HaLeft" textVAlign="VaTop" textWordWrap="True" textStyles="[]" useDefaultTextSize="False">
          <text>%E5%86%99%E4%B8%8B%E4%BD%A0%E7%9A%84%E7%BB%8F%E9%AA%8C%E3%80%81%E6%95%85%E4%BA%8B%E6%88%96%E9%97%AE%E9%A2%98</text>
        </textSet>
        <selectedIndex>-1</selectedIndex>
        <selectedColor>4282501083</selectedColor>
        <textPadding>0</textPadding>
      </controlProperties>
    </control>
    <control controlID="BD1CBC77-B8CE-4DE1-B571-B142EAC1B866" controlTypeID="Image" isShow="True" caption="%E5%9B%BE%E7%89%87" x="6" y="592" w="48" h="48" measuredW="150" measuredH="150" zOrder="7" locked="False" sizeLocked="False">
      <controlProperties>
        <basic color="4294967295" borderVisible="False" borderColor="4278190080" isAutoSize="False" status="MsEnabled" opacity="1" isCommentCom="False" canMove="True" alias="" rotation="0"/>
        <states/>
        <verticalScrollbarShow>False</verticalScrollbarShow>
        <verticalScrollbarProgress>30</verticalScrollbarProgress>
        <horizontalScrollbarShow>False</horizontalScrollbarShow>
        <horizontalScrollbarProgress>30</horizontalScrollbarProgress>
        <links eventType="AtClick" animate="AmPushRight" animateAutoDelay="0" animateDuration="500">
          <link targetPageID="" linkType="ltPageLink" isApplyIncludePage="False" title="%E9%93%BE%E6%8E%A5">
            <area shape="0" alt="" ID="{3AB5B0C0-1821-46D4-91C9-31C37632BD5A}" coords="(0,0,48,48)"/>
          </link>
        </links>
        <interactiveData>
          <entry title="">
            <area shape="0" alt="" ID="{8050C85A-D499-48BC-9043-DE04B8792992}" coords="(0,0,48,48)"/>
            <events title=""/>
          </entry>
        </interactiveData>
        <rotationAngle>TdZero</rotationAngle>
        <clipShapeType>SbRectangle</clipShapeType>
        <radius>0</radius>
        <radiusIsPercent>True</radiusIsPercent>
        <filterType>MfNone</filterType>
        <filterPencilValue>2</filterPencilValue>
        <filterSketchValue>5</filterSketchValue>
        <URL/>
        <FlipHorizontal>False</FlipHorizontal>
        <FlipVertical>False</FlipVertical>
        <fitMode>2</fitMode>
      </controlProperties>
    </control>
    <control controlID="A74EBA2B-E1F9-4F5D-94C6-AB2B959A24F1" controlTypeID="Button" isShow="True" caption="%E6%8C%89%E9%92%AE" x="301" y="14" w="53" h="31" measuredW="78" measuredH="36" zOrder="8" locked="False" sizeLocked="False">
      <controlProperties>
        <basic color="4294967295" borderVisible="True" borderColor="4278190080" isAutoSize="False" status="MsEnabled" opacity="1" isCommentCom="False" canMove="True" alias="" rotation="0"/>
        <states/>
        <verticalScrollbarShow>False</verticalScrollbarShow>
        <verticalScrollbarProgress>30</verticalScrollbarProgress>
        <horizontalScrollbarShow>False</horizontalScrollbarShow>
        <horizontalScrollbarProgress>30</horizontalScrollbarProgress>
        <links eventType="AtClick" animate="AmPushRight" animateAutoDelay="0" animateDuration="500">
          <link targetPageID="" linkType="ltPageLink" isApplyIncludePage="False" title="%E9%93%BE%E6%8E%A5">
            <area shape="0" alt="" ID="{538EEE11-4E62-4354-B9C9-2DF6AA23E959}" coords="(0,0,53,31)"/>
          </link>
        </links>
        <interactiveData>
          <entry title="">
            <area shape="0" alt="" ID="{DCD7410E-29DE-4384-961C-04BD8A73226D}" coords="(0,0,53,31)"/>
            <events title=""/>
          </entry>
        </interactiveData>
        <textSet textColor="4288256409" textSize="14" textFontFamily="%E5%BE%AE%E8%BD%AF%E9%9B%85%E9%BB%91" lineSpacingMultiple="1" textAlign="HaCenter" textVAlign="VaMiddle" textWordWrap="True" textStyles="[]" useDefaultTextSize="True">
          <text>%E5%AE%8C%E6%88%90</text>
        </textSet>
        <selectedIndex>-1</selectedIndex>
        <selectedColor>4282501083</selectedColor>
        <textPadding>0</textPadding>
        <radius>0</radius>
        <radiusIsPercent>True</radiusIsPercent>
        <buttonStatus>BsNormal</buttonStatus>
        <thickness>1</thickness>
        <isAutoTextColor>False</isAutoTextColor>
        <borderColor>4278190080</borderColor>
      </controlProperties>
    </control>
    <control controlID="86993112-1AE4-4C73-A6EF-5605D2491535" controlTypeID="Label" isShow="True" caption="%E5%8D%95%E8%A1%8C%E6%96%87%E5%AD%97" x="152" y="513" w="56" h="19" measuredW="0" measuredH="0" zOrder="9" locked="False" sizeLocked="False">
      <controlProperties>
        <basic color="16777215" borderVisible="True" borderColor="0" isAutoSize="True" status="MsEnabled" opacity="1" isCommentCom="False" canMove="True" alias="" rotation="0"/>
        <states/>
        <verticalScrollbarShow>False</verticalScrollbarShow>
        <verticalScrollbarProgress>30</verticalScrollbarProgress>
        <horizontalScrollbarShow>False</horizontalScrollbarShow>
        <horizontalScrollbarProgress>30</horizontalScrollbarProgress>
        <links eventType="AtClick" animate="AmNone" animateAutoDelay="0" animateDuration="500">
          <link targetPageID="3A747663-5DFF-4671-86A8-6FF196B5E3F4" linkType="ltPageLink" isApplyIncludePage="False" title="%E5%88%9B%E5%BB%BA%E5%B8%96%E5%AD%901">
            <area shape="0" alt="" ID="{CD501A41-9165-4D67-8572-B042FD7258CC}" coords="(0,0,56,19)"/>
          </link>
        </links>
        <interactiveData>
          <entry title="">
            <area shape="0" alt="" ID="{A86DB5C7-4E90-4D97-AD3A-7BD304EE2CE0}" coords="(0,0,56,19)"/>
            <events title=""/>
          </entry>
        </interactiveData>
        <textSet textColor="4294901760" textSize="14" textFontFamily="%E5%BE%AE%E8%BD%AF%E9%9B%85%E9%BB%91" lineSpacingMultiple="1" textAlign="HaLeft" textVAlign="VaTop" textWordWrap="True" textStyles="[]" useDefaultTextSize="True">
          <text>%E7%BC%96%E8%BE%91%E6%A0%B7%E5%BC%8F</text>
        </textSet>
        <selectedIndex>-1</selectedIndex>
        <selectedColor>4282501083</selectedColor>
        <textPadding>0</textPadding>
      </controlProperties>
    </control>
    <control controlID="649F21C7-5DC1-4258-88A8-43ED610891BA" controlTypeID="StickyNote" isShow="True" caption="%E4%BE%BF%E7%AD%BE%E6%9D%A1" x="-243" y="45" w="183" h="468" measuredW="109" measuredH="123" zOrder="10" locked="False" sizeLocked="False">
      <controlProperties>
        <basic color="4294033970" borderVisible="True" borderColor="0" isAutoSize="False" status="MsEnabled" opacity="1" isCommentCom="True" canMove="True" alias="" rotation="0"/>
        <states/>
        <verticalScrollbarShow>False</verticalScrollbarShow>
        <verticalScrollbarProgress>30</verticalScrollbarProgress>
        <horizontalScrollbarShow>False</horizontalScrollbarShow>
        <horizontalScrollbarProgress>30</horizontalScrollbarProgress>
        <links eventType="AtClick" animate="AmPushLeft" animateAutoDelay="0" animateDuration="500">
          <link targetPageID="" linkType="ltPageLink" isApplyIncludePage="False" title="%E9%93%BE%E6%8E%A5">
            <area shape="0" alt="" ID="{D610007B-FD0F-420E-8900-8573E3B7C27A}" coords="(0,0,183,468)"/>
          </link>
        </links>
        <interactiveData>
          <entry title="">
            <area shape="0" alt="" ID="{B16D3089-32C2-4E9B-AEBA-0F46AFC05337}" coords="(0,0,183,468)"/>
            <events title=""/>
          </entry>
        </interactiveData>
        <textSet textColor="4278190080" textSize="14" textFontFamily="%E5%BE%AE%E8%BD%AF%E9%9B%85%E9%BB%91" lineSpacingMultiple="1" textAlign="HaLeft" textVAlign="VaTop" textWordWrap="True" textStyles="[]" useDefaultTextSize="True">
          <text>1%E3%80%81%E5%AF%BC%E8%88%AA%E6%A0%8F%0D%0A-%E8%AE%B2%E8%BF%B0title%0D%0A-%E5%AE%8C%E6%88%90%E6%8C%89%E9%92%AE%0D%0A%E6%A0%87%E9%A2%98%E5%92%8C%E6%AD%A3%E6%96%87%E6%9C%AA%E5%A1%AB%E5%86%99%E6%97%B6%EF%BC%8C%E6%8C%89%E9%92%AE%E7%81%B0%E8%89%B2%E4%B8%8D%E5%8F%AF%E7%82%B9%E5%87%BB%0D%0A%0D%0A2%E3%80%81%E8%AE%B2%E8%BF%B0%E6%A0%87%E9%A2%98%0D%0A-20%E4%B8%AA%E4%B8%AD%E6%96%87%E5%AD%97%E7%AC%A6%E5%86%85%0D%0A%0D%0A3%E3%80%81%E8%AE%B2%E8%BF%B0%E6%AD%A3%E6%96%87%0D%0A-5000%E4%B8%AA%E4%B8%AD%E6%96%87%E5%AD%97%E7%AC%A6%E5%86%85%0D%0A%0D%0A4%E3%80%81%E5%9B%BE%E7%89%87%0D%0A-%E6%9C%80%E5%A4%9A%E6%B7%BB%E5%8A%A09%E5%BC%A0%0D%0A-%E8%AE%B2%E8%BF%B0%E5%8F%91%E5%B8%83%E5%90%8E%EF%BC%8C%E6%B7%BB%E5%8A%A0%E7%9A%84%E5%9B%BE%E7%89%87%E8%B7%9F%E5%9C%A8%E8%AE%B2%E8%BF%B0%E6%AD%A3%E6%96%87%E5%90%8E%E9%9D%A2%EF%BC%8C%E6%A0%B9%E6%8D%AE%E5%AE%BD%E5%BA%A6%E7%AD%89%E6%AF%94%E4%BE%8B%E5%85%A8%E5%9B%BE%E6%98%BE%E7%A4%BA%EF%BC%8C%E9%A1%BA%E5%BA%8F%E6%8E%92%E5%88%97%0D%0A%0D%0A*%E5%8F%AF%E4%B8%80%E6%AC%A1%E6%80%A7%E7%9B%B4%E6%8E%A5%E5%8B%BE%E9%80%89%E6%B7%BB%E5%8A%A0%E5%A4%9A%E5%BC%A0%0D%0A%0D%0A</text>
        </textSet>
        <selectedIndex>-1</selectedIndex>
        <selectedColor>4282501083</selectedColor>
        <textPadding>0</textPadding>
        <isShowTabBar>True</isShowTabBar>
      </controlProperties>
    </control>
    <control controlID="B083D979-AA61-423F-B488-193E613E4D0B" controlTypeID="Icon" isShow="True" caption="%E5%9B%BE%E6%A0%87" x="64" y="605" w="24" h="24" measuredW="32" measuredH="32" zOrder="11" locked="False" sizeLocked="False">
      <controlProperties>
        <basic color="4282664004" borderVisible="True" borderColor="0" isAutoSize="False" status="MsEnabled" opacity="1" isCommentCom="False" canMove="True" alias="" rotation="0"/>
        <states/>
        <verticalScrollbarShow>False</verticalScrollbarShow>
        <verticalScrollbarProgress>30</verticalScrollbarProgress>
        <horizontalScrollbarShow>False</horizontalScrollbarShow>
        <horizontalScrollbarProgress>30</horizontalScrollbarProgress>
        <links eventType="AtClick" animate="AmSlideUp" animateAutoDelay="0" animateDuration="500">
          <link targetPageID="" linkType="ltPageLink" isApplyIncludePage="False" title="%E9%93%BE%E6%8E%A5">
            <area shape="0" alt="" ID="{6332027A-9CF1-4160-AD69-5A04891CC5C4}" coords="(0,0,24,24)"/>
          </link>
        </links>
        <interactiveData>
          <entry title="">
            <area shape="0" alt="" ID="{159C786A-1282-40E1-8E1B-EDA6352AF55B}" coords="(0,0,24,24)"/>
            <events title=""/>
          </entry>
        </interactiveData>
        <rotationAngle>TdZero</rotationAngle>
        <icon>
          <ID>Plus.png</ID>
          <iconFontName/>
          <iconCode>-1</iconCode>
        </icon>
        <URL/>
        <FlipHorizontal>False</FlipHorizontal>
        <FlipVertical>False</FlipVertical>
      </controlProperties>
    </control>
    <control controlID="C1E0D8B1-F04C-4B68-9FD3-B6E59A3D6649" controlTypeID="StickyNote" isShow="True" caption="%E4%BE%BF%E7%AD%BE%E6%9D%A1" x="411" y="113" w="176" h="194" measuredW="109" measuredH="123" zOrder="12" locked="False" sizeLocked="False">
      <controlProperties>
        <basic color="4294927974" borderVisible="True" borderColor="0" isAutoSize="False" status="MsEnabled" opacity="1" isCommentCom="True" canMove="True" alias="" rotation="0"/>
        <states/>
        <verticalScrollbarShow>False</verticalScrollbarShow>
        <verticalScrollbarProgress>30</verticalScrollbarProgress>
        <horizontalScrollbarShow>False</horizontalScrollbarShow>
        <horizontalScrollbarProgress>30</horizontalScrollbarProgress>
        <links eventType="AtClick" animate="AmNone" animateAutoDelay="0" animateDuration="500">
          <link targetPageID="" linkType="ltPageLink" isApplyIncludePage="False" title="%E9%93%BE%E6%8E%A5">
            <area shape="0" alt="" ID="{2EF46E35-FB7C-4A60-BE08-D4824A5181E3}" coords="(0,0,176,194)"/>
          </link>
        </links>
        <interactiveData>
          <entry title="">
            <area shape="0" alt="" ID="{5A01F186-96D8-4CB2-9254-EE7CFDFABA9E}" coords="(0,0,176,194)"/>
            <events title=""/>
          </entry>
        </interactiveData>
        <textSet textColor="4278190080" textSize="14" textFontFamily="%E5%BE%AE%E8%BD%AF%E9%9B%85%E9%BB%91" lineSpacingMultiple="1" textAlign="HaLeft" textVAlign="VaTop" textWordWrap="True" textStyles="[]" useDefaultTextSize="True">
          <text>1%E3%80%81%E7%82%B9%E5%87%BB%E5%AE%8C%E6%88%90%EF%BC%8C%E5%87%BA%E7%8E%B0%E5%8A%A0%E8%BD%BD%E5%8A%A8%E7%94%BB%0D%0A-%E6%88%90%E5%8A%9F%E5%90%8E%E8%BF%94%E5%9B%9E%E9%A6%96%E9%A1%B5-%E5%B8%96%E5%AD%90%EF%BC%8C%E9%A1%B5%E9%9D%A2%E5%88%B7%E6%96%B0%0D%0A%0D%0A%0D%0A2%E3%80%81%E7%82%B9%E5%87%BB%E8%BF%94%E5%9B%9E%EF%BC%8C%E5%BC%B9%E7%AA%97%E7%A1%AE%E8%AE%A4</text>
        </textSet>
        <selectedIndex>-1</selectedIndex>
        <selectedColor>4282501083</selectedColor>
        <textPadding>0</textPadding>
        <isShowTabBar>True</isShowTabBar>
      </controlProperties>
    </control>
  </controls>
  <param>
    <backgroundColor>4294967295</backgroundColor>
    <fontFamily>%E5%BE%AE%E8%BD%AF%E9%9B%85%E9%BB%91</fontFamily>
    <guideLines/>
  </param>
</mockup>