<mockup version="4.2" platform="MtMobile" defaultW="360" defaultH="640" from="FmLocal" screenOrientation="MoPortrait" mobileScreenScale="1.77777779102325" minAllowVersion="4.1" ID="CF141207-8B2F-48F3-BF63-78E3F6C6C28B" measureW="360" measureH="640" clipArea="(0,0,0,0)">
  <controls controlCount="12">
    <control controlID="843DABBC-695B-409A-BED5-CE4713E68F10" controlTypeID="Shape" isShow="True" caption="%E5%BD%A2%E7%8A%B6" x="0" y="0" w="360" h="45" measuredW="120" measuredH="100" zOrder="0" locked="False" sizeLocked="False">
      <controlProperties>
        <basic color="4294967295" borderVisible="True" borderColor="4284900966" isAutoSize="False" status="MsEnabled" opacity="1" isCommentCom="False" canMove="True" alias="" rotation="0"/>
        <states/>
        <verticalScrollbarShow>False</verticalScrollbarShow>
        <verticalScrollbarProgress>0</verticalScrollbarProgress>
        <horizontalScrollbarShow>False</horizontalScrollbarShow>
        <horizontalScrollbarProgress>0</horizontalScrollbarProgress>
        <links eventType="AtClick" animate="AmPushLeft" animateAutoDelay="0" animateDuration="500">
          <link targetPageID="" linkType="ltPageLink" isApplyIncludePage="False" title="%E9%93%BE%E6%8E%A5">
            <area shape="0" alt="" ID="{218B6023-D4AA-4920-8F39-8E690A6E413D}" coords="(0,0,360,45)"/>
          </link>
        </links>
        <interactiveData>
          <entry title="">
            <area shape="0" alt="" ID="{21E745EC-168D-40E5-8DF9-8EE50C58D369}" coords="(0,0,360,45)"/>
            <events title=""/>
          </entry>
        </interactiveData>
        <textSet textColor="4278190080" textSize="14" textFontFamily="%E5%BE%AE%E8%BD%AF%E9%9B%85%E9%BB%91" lineSpacingMultiple="1" textAlign="HaCenter" textVAlign="VaMiddle" textWordWrap="True" textStyles="[]" useDefaultTextSize="False">
          <text>%E6%83%A0%E7%BE%8E</text>
        </textSet>
        <selectedIndex>-1</selectedIndex>
        <selectedColor>4282501083</selectedColor>
        <textPadding>0</textPadding>
        <shapeBorderType>SbRectangle</shapeBorderType>
        <triangleType>TdZero</triangleType>
        <dashMode>SdSolid</dashMode>
        <rectangleBorderLeftVisible>True</rectangleBorderLeftVisible>
        <rectangleBorderRightVisible>True</rectangleBorderRightVisible>
        <rectangleBorderTopVisible>True</rectangleBorderTopVisible>
        <rectangleBorderBottomVisible>True</rectangleBorderBottomVisible>
        <radius>0</radius>
        <radiusIsPercent>False</radiusIsPercent>
        <thickness>1</thickness>
      </controlProperties>
    </control>
    <control controlID="9C9335DD-6B34-407A-84C2-BF403C7C698D" controlTypeID="Icon" isShow="True" caption="%E5%9B%BE%E6%A0%87" x="12" y="10" w="24" h="24" measuredW="32" measuredH="32" zOrder="1" locked="False" sizeLocked="False">
      <controlProperties>
        <basic color="4284900966" borderVisible="True" borderColor="4284900966" isAutoSize="False" status="MsEnabled" opacity="1" isCommentCom="False" canMove="True" alias="" rotation="0"/>
        <states/>
        <verticalScrollbarShow>False</verticalScrollbarShow>
        <verticalScrollbarProgress>0</verticalScrollbarProgress>
        <horizontalScrollbarShow>False</horizontalScrollbarShow>
        <horizontalScrollbarProgress>0</horizontalScrollbarProgress>
        <links eventType="AtClick" animate="AmPushRight" animateAutoDelay="0" animateDuration="500">
          <link targetPageID="6EF14506-5BB2-443A-B811-C2652811FF34" linkType="ltPageLink" isApplyIncludePage="False" title="7.1.1%E8%BE%BE%E4%BA%BA%E8%AF%A6%E6%83%85%E9%A1%B5">
            <area shape="0" alt="" ID="{E61BE6A2-004E-4E23-9F67-DFD31555FE29}" coords="(0,0,24,24)"/>
          </link>
        </links>
        <interactiveData>
          <entry title="">
            <area shape="0" alt="" ID="{C3558CBC-3C8D-4CA8-9984-2C64769F9B2B}" coords="(0,0,24,24)"/>
            <events title=""/>
          </entry>
        </interactiveData>
        <rotationAngle>TdZero</rotationAngle>
        <icon>
          <ID>Back.png</ID>
          <iconFontName/>
          <iconCode>-1</iconCode>
        </icon>
        <URL/>
        <FlipHorizontal>False</FlipHorizontal>
        <FlipVertical>False</FlipVertical>
      </controlProperties>
    </control>
    <control controlID="15DD1940-E353-4819-A3FD-D0B3BBD8CBA2" controlTypeID="Shape" isShow="True" caption="%E5%BD%A2%E7%8A%B6" x="0" y="599" w="276" h="41" measuredW="120" measuredH="100" zOrder="2" locked="False" sizeLocked="False">
      <controlProperties>
        <basic color="4294967295" borderVisible="True" borderColor="4284900966" isAutoSize="False" status="MsEnabled" opacity="1" isCommentCom="False" canMove="True" alias="" rotation="0"/>
        <states/>
        <verticalScrollbarShow>False</verticalScrollbarShow>
        <verticalScrollbarProgress>0</verticalScrollbarProgress>
        <horizontalScrollbarShow>False</horizontalScrollbarShow>
        <horizontalScrollbarProgress>0</horizontalScrollbarProgress>
        <links eventType="AtClick" animate="AmPushLeft" animateAutoDelay="0" animateDuration="500">
          <link targetPageID="" linkType="ltPageLink" isApplyIncludePage="False" title="%E9%93%BE%E6%8E%A5">
            <area shape="0" alt="" ID="{2A545619-80A3-41C2-A06A-E269E3A975C0}" coords="(0,0,276,41)"/>
          </link>
        </links>
        <interactiveData>
          <entry title="">
            <area shape="0" alt="" ID="{3E061BF1-A5D5-45B6-ADBD-27BBAC1EDD78}" coords="(0,0,276,41)"/>
            <events title=""/>
          </entry>
        </interactiveData>
        <textSet textColor="4278190080" textSize="12" textFontFamily="%E5%BE%AE%E8%BD%AF%E9%9B%85%E9%BB%91" lineSpacingMultiple="1" textAlign="HaCenter" textVAlign="VaMiddle" textWordWrap="True" textStyles="[]" useDefaultTextSize="True"/>
        <selectedIndex>-1</selectedIndex>
        <selectedColor>4282501083</selectedColor>
        <textPadding>0</textPadding>
        <shapeBorderType>SbRectangle</shapeBorderType>
        <triangleType>TdZero</triangleType>
        <dashMode>SdSolid</dashMode>
        <rectangleBorderLeftVisible>True</rectangleBorderLeftVisible>
        <rectangleBorderRightVisible>True</rectangleBorderRightVisible>
        <rectangleBorderTopVisible>True</rectangleBorderTopVisible>
        <rectangleBorderBottomVisible>True</rectangleBorderBottomVisible>
        <radius>0</radius>
        <radiusIsPercent>False</radiusIsPercent>
        <thickness>1</thickness>
      </controlProperties>
    </control>
    <control controlID="6AF9A903-3266-4AEF-9A25-09B0E85D5D43" controlTypeID="Shape" isShow="True" caption="%E5%BD%A2%E7%8A%B6" x="286" y="599" w="74" h="41" measuredW="120" measuredH="100" zOrder="3" locked="False" sizeLocked="False">
      <controlProperties>
        <basic color="4294967295" borderVisible="True" borderColor="4284900966" isAutoSize="False" status="MsEnabled" opacity="1" isCommentCom="False" canMove="True" alias="" rotation="0"/>
        <states/>
        <verticalScrollbarShow>False</verticalScrollbarShow>
        <verticalScrollbarProgress>0</verticalScrollbarProgress>
        <horizontalScrollbarShow>False</horizontalScrollbarShow>
        <horizontalScrollbarProgress>0</horizontalScrollbarProgress>
        <links eventType="AtClick" animate="AmPushLeft" animateAutoDelay="0" animateDuration="500">
          <link targetPageID="" linkType="ltPageLink" isApplyIncludePage="False" title="%E9%93%BE%E6%8E%A5">
            <area shape="0" alt="" ID="{2A545619-80A3-41C2-A06A-E269E3A975C0}" coords="(0,0,74,41)"/>
          </link>
        </links>
        <interactiveData>
          <entry title="">
            <area shape="0" alt="" ID="{3E061BF1-A5D5-45B6-ADBD-27BBAC1EDD78}" coords="(0,0,74,41)"/>
            <events title=""/>
          </entry>
        </interactiveData>
        <textSet textColor="4278190080" textSize="12" textFontFamily="%E5%BE%AE%E8%BD%AF%E9%9B%85%E9%BB%91" lineSpacingMultiple="1" textAlign="HaCenter" textVAlign="VaMiddle" textWordWrap="True" textStyles="[]" useDefaultTextSize="True">
          <text>%E5%8F%91%E9%80%81</text>
        </textSet>
        <selectedIndex>-1</selectedIndex>
        <selectedColor>4282501083</selectedColor>
        <textPadding>0</textPadding>
        <shapeBorderType>SbRectangle</shapeBorderType>
        <triangleType>TdZero</triangleType>
        <dashMode>SdSolid</dashMode>
        <rectangleBorderLeftVisible>True</rectangleBorderLeftVisible>
        <rectangleBorderRightVisible>True</rectangleBorderRightVisible>
        <rectangleBorderTopVisible>True</rectangleBorderTopVisible>
        <rectangleBorderBottomVisible>True</rectangleBorderBottomVisible>
        <radius>0</radius>
        <radiusIsPercent>False</radiusIsPercent>
        <thickness>1</thickness>
      </controlProperties>
    </control>
    <control controlID="F9B3F98B-8DAF-426B-9450-1E27EAE3113F" controlTypeID="Shape" isShow="True" caption="%E5%BD%A2%E7%8A%B6" x="0" y="0" w="360" h="640" measuredW="120" measuredH="100" zOrder="4" locked="False" sizeLocked="False">
      <controlProperties>
        <basic color="4287006342" borderVisible="True" borderColor="4284900966" isAutoSize="False" status="MsEnabled" opacity="0.400000005960464" isCommentCom="False" canMove="True" alias="" rotation="0"/>
        <states/>
        <verticalScrollbarShow>False</verticalScrollbarShow>
        <verticalScrollbarProgress>0</verticalScrollbarProgress>
        <horizontalScrollbarShow>False</horizontalScrollbarShow>
        <horizontalScrollbarProgress>0</horizontalScrollbarProgress>
        <links eventType="AtClick" animate="AmPushLeft" animateAutoDelay="0" animateDuration="500">
          <link targetPageID="" linkType="ltPageLink" isApplyIncludePage="False" title="%E9%93%BE%E6%8E%A5">
            <area shape="0" alt="" ID="{641797CA-8E0E-4684-8ADF-67388A25B49B}" coords="(0,0,360,640)"/>
          </link>
        </links>
        <interactiveData>
          <entry title="">
            <area shape="0" alt="" ID="{8F9BA3AB-A28E-48B8-9CB9-77F3B443281D}" coords="(0,0,360,640)"/>
            <events title=""/>
          </entry>
        </interactiveData>
        <textSet textColor="4278190080" textSize="12" textFontFamily="%E5%BE%AE%E8%BD%AF%E9%9B%85%E9%BB%91" lineSpacingMultiple="1" textAlign="HaCenter" textVAlign="VaMiddle" textWordWrap="True" textStyles="[]" useDefaultTextSize="True"/>
        <selectedIndex>-1</selectedIndex>
        <selectedColor>4282501083</selectedColor>
        <textPadding>0</textPadding>
        <shapeBorderType>SbRectangle</shapeBorderType>
        <triangleType>TdZero</triangleType>
        <dashMode>SdSolid</dashMode>
        <rectangleBorderLeftVisible>True</rectangleBorderLeftVisible>
        <rectangleBorderRightVisible>True</rectangleBorderRightVisible>
        <rectangleBorderTopVisible>True</rectangleBorderTopVisible>
        <rectangleBorderBottomVisible>True</rectangleBorderBottomVisible>
        <radius>0</radius>
        <radiusIsPercent>False</radiusIsPercent>
        <thickness>1</thickness>
      </controlProperties>
    </control>
    <control controlID="278ACB8C-5A5C-4374-AEDA-95482BFDB4D2" controlTypeID="Shape" isShow="True" caption="%E5%BD%A2%E7%8A%B6" x="51" y="216" w="257" h="140" measuredW="120" measuredH="100" zOrder="5" locked="False" sizeLocked="False">
      <controlProperties>
        <basic color="4294967295" borderVisible="True" borderColor="4284900966" isAutoSize="False" status="MsEnabled" opacity="1" isCommentCom="False" canMove="True" alias="" rotation="0"/>
        <states/>
        <verticalScrollbarShow>False</verticalScrollbarShow>
        <verticalScrollbarProgress>0</verticalScrollbarProgress>
        <horizontalScrollbarShow>False</horizontalScrollbarShow>
        <horizontalScrollbarProgress>0</horizontalScrollbarProgress>
        <links eventType="AtClick" animate="AmPushLeft" animateAutoDelay="0" animateDuration="500">
          <link targetPageID="" linkType="ltPageLink" isApplyIncludePage="False" title="%E9%93%BE%E6%8E%A5">
            <area shape="0" alt="" ID="{6516FF11-A631-4D38-A0DE-0820B3878396}" coords="(0,0,257,140)"/>
          </link>
        </links>
        <interactiveData>
          <entry title="">
            <area shape="0" alt="" ID="{861D7BDF-9D5B-41E5-A32C-D4C6D3B62437}" coords="(0,0,257,140)"/>
            <events title=""/>
          </entry>
        </interactiveData>
        <textSet textColor="4278190080" textSize="12" textFontFamily="%E5%BE%AE%E8%BD%AF%E9%9B%85%E9%BB%91" lineSpacingMultiple="1" textAlign="HaCenter" textVAlign="VaMiddle" textWordWrap="True" textStyles="[]" useDefaultTextSize="True"/>
        <selectedIndex>-1</selectedIndex>
        <selectedColor>4282501083</selectedColor>
        <textPadding>0</textPadding>
        <shapeBorderType>SbRectangle</shapeBorderType>
        <triangleType>TdZero</triangleType>
        <dashMode>SdSolid</dashMode>
        <rectangleBorderLeftVisible>True</rectangleBorderLeftVisible>
        <rectangleBorderRightVisible>True</rectangleBorderRightVisible>
        <rectangleBorderTopVisible>True</rectangleBorderTopVisible>
        <rectangleBorderBottomVisible>True</rectangleBorderBottomVisible>
        <radius>0</radius>
        <radiusIsPercent>False</radiusIsPercent>
        <thickness>1</thickness>
      </controlProperties>
    </control>
    <control controlID="27447972-FC35-4F58-A014-E27D4058E951" controlTypeID="Label" isShow="True" caption="%E5%8D%95%E8%A1%8C%E6%96%87%E5%AD%97" x="80" y="277" w="196" h="19" measuredW="0" measuredH="0" zOrder="6" locked="False" sizeLocked="False">
      <controlProperties>
        <basic color="0" borderVisible="True" borderColor="4284900966" isAutoSize="True" status="MsEnabled" opacity="1" isCommentCom="False" canMove="True" alias="" rotation="0"/>
        <states/>
        <verticalScrollbarShow>False</verticalScrollbarShow>
        <verticalScrollbarProgress>0</verticalScrollbarProgress>
        <horizontalScrollbarShow>False</horizontalScrollbarShow>
        <horizontalScrollbarProgress>0</horizontalScrollbarProgress>
        <links eventType="AtClick" animate="AmPushLeft" animateAutoDelay="0" animateDuration="500">
          <link targetPageID="" linkType="ltPageLink" isApplyIncludePage="False" title="%E9%93%BE%E6%8E%A5">
            <area shape="0" alt="" ID="{B5FCF227-B351-452E-A129-91CCA85BC998}" coords="(0,0,196,19)"/>
          </link>
        </links>
        <interactiveData>
          <entry title="">
            <area shape="0" alt="" ID="{FBD9CDCA-CAC2-40CB-98A1-376C2642C432}" coords="(0,0,196,19)"/>
            <events title=""/>
          </entry>
        </interactiveData>
        <textSet textColor="4278190080" textSize="14" textFontFamily="%E5%BE%AE%E8%BD%AF%E9%9B%85%E9%BB%91" lineSpacingMultiple="1" textAlign="HaLeft" textVAlign="VaTop" textWordWrap="True" textStyles="[]" useDefaultTextSize="False">
          <text>%E6%94%AF%E4%BB%98%E5%A4%B1%E8%B4%A5%EF%BC%8C%E6%9A%82%E6%97%B6%E4%B8%8D%E8%83%BD%E5%92%8C%E5%AF%BC%E5%B8%88%E7%A7%81%E8%81%8A</text>
        </textSet>
        <selectedIndex>-1</selectedIndex>
        <selectedColor>4282501083</selectedColor>
        <textPadding>0</textPadding>
      </controlProperties>
    </control>
    <control controlID="AF9C7915-6EEB-41B9-A866-DA26C6A709BC" controlTypeID="Shape" isShow="True" caption="%E5%BD%A2%E7%8A%B6" x="51" y="314" w="130" h="42" measuredW="120" measuredH="100" zOrder="7" locked="False" sizeLocked="False">
      <controlProperties>
        <basic color="4294967295" borderVisible="True" borderColor="4284900966" isAutoSize="False" status="MsEnabled" opacity="1" isCommentCom="False" canMove="True" alias="" rotation="0"/>
        <states/>
        <verticalScrollbarShow>False</verticalScrollbarShow>
        <verticalScrollbarProgress>0</verticalScrollbarProgress>
        <horizontalScrollbarShow>False</horizontalScrollbarShow>
        <horizontalScrollbarProgress>0</horizontalScrollbarProgress>
        <links eventType="AtClick" animate="AmPushLeft" animateAutoDelay="0" animateDuration="500">
          <link targetPageID="" linkType="ltPageLink" isApplyIncludePage="False" title="%E9%93%BE%E6%8E%A5">
            <area shape="0" alt="" ID="{2330C2C7-CC25-4E1E-AF2C-4A92FBFA403D}" coords="(0,0,130,42)"/>
          </link>
        </links>
        <interactiveData>
          <entry title="">
            <area shape="0" alt="" ID="{751769F6-F8FC-4C25-96FC-87BFD21D9257}" coords="(0,0,130,42)"/>
            <events title=""/>
          </entry>
        </interactiveData>
        <textSet textColor="4278190080" textSize="12" textFontFamily="%E5%BE%AE%E8%BD%AF%E9%9B%85%E9%BB%91" lineSpacingMultiple="1" textAlign="HaCenter" textVAlign="VaMiddle" textWordWrap="True" textStyles="[]" useDefaultTextSize="True">
          <text>%E5%8F%96%E6%B6%88</text>
        </textSet>
        <selectedIndex>-1</selectedIndex>
        <selectedColor>4282501083</selectedColor>
        <textPadding>0</textPadding>
        <shapeBorderType>SbRectangle</shapeBorderType>
        <triangleType>TdZero</triangleType>
        <dashMode>SdSolid</dashMode>
        <rectangleBorderLeftVisible>True</rectangleBorderLeftVisible>
        <rectangleBorderRightVisible>True</rectangleBorderRightVisible>
        <rectangleBorderTopVisible>True</rectangleBorderTopVisible>
        <rectangleBorderBottomVisible>True</rectangleBorderBottomVisible>
        <radius>0</radius>
        <radiusIsPercent>False</radiusIsPercent>
        <thickness>1</thickness>
      </controlProperties>
    </control>
    <control controlID="1FD2A0BA-9907-4BFD-8B5C-0F0C52EED215" controlTypeID="Shape" isShow="True" caption="%E5%BD%A2%E7%8A%B6" x="181" y="314" w="127" h="42" measuredW="120" measuredH="100" zOrder="8" locked="False" sizeLocked="False">
      <controlProperties>
        <basic color="4294967295" borderVisible="True" borderColor="4284900966" isAutoSize="False" status="MsEnabled" opacity="1" isCommentCom="False" canMove="True" alias="" rotation="0"/>
        <states/>
        <verticalScrollbarShow>False</verticalScrollbarShow>
        <verticalScrollbarProgress>0</verticalScrollbarProgress>
        <horizontalScrollbarShow>False</horizontalScrollbarShow>
        <horizontalScrollbarProgress>0</horizontalScrollbarProgress>
        <links eventType="AtClick" animate="AmPushLeft" animateAutoDelay="0" animateDuration="500">
          <link targetPageID="" linkType="ltPageLink" isApplyIncludePage="False" title="%E9%93%BE%E6%8E%A5">
            <area shape="0" alt="" ID="{2330C2C7-CC25-4E1E-AF2C-4A92FBFA403D}" coords="(0,0,127,42)"/>
          </link>
        </links>
        <interactiveData>
          <entry title="">
            <area shape="0" alt="" ID="{751769F6-F8FC-4C25-96FC-87BFD21D9257}" coords="(0,0,127,42)"/>
            <events title=""/>
          </entry>
        </interactiveData>
        <textSet textColor="4278190080" textSize="12" textFontFamily="%E5%BE%AE%E8%BD%AF%E9%9B%85%E9%BB%91" lineSpacingMultiple="1" textAlign="HaCenter" textVAlign="VaMiddle" textWordWrap="True" textStyles="[]" useDefaultTextSize="True">
          <text>%E9%87%8D%E6%96%B0%E6%94%AF%E4%BB%98</text>
        </textSet>
        <selectedIndex>-1</selectedIndex>
        <selectedColor>4282501083</selectedColor>
        <textPadding>0</textPadding>
        <shapeBorderType>SbRectangle</shapeBorderType>
        <triangleType>TdZero</triangleType>
        <dashMode>SdSolid</dashMode>
        <rectangleBorderLeftVisible>True</rectangleBorderLeftVisible>
        <rectangleBorderRightVisible>True</rectangleBorderRightVisible>
        <rectangleBorderTopVisible>True</rectangleBorderTopVisible>
        <rectangleBorderBottomVisible>True</rectangleBorderBottomVisible>
        <radius>0</radius>
        <radiusIsPercent>False</radiusIsPercent>
        <thickness>1</thickness>
      </controlProperties>
    </control>
    <control controlID="56257930-3E78-40F3-9252-F0BBA67A2927" controlTypeID="StickyNote" isShow="True" caption="%E4%BE%BF%E7%AD%BE%E6%9D%A1" x="-259" y="46" w="222" h="310" measuredW="109" measuredH="123" zOrder="9" locked="False" sizeLocked="False">
      <controlProperties>
        <basic color="4294033970" borderVisible="True" borderColor="4284900966" isAutoSize="False" status="MsEnabled" opacity="1" isCommentCom="True" canMove="True" alias="" rotation="0"/>
        <states/>
        <verticalScrollbarShow>False</verticalScrollbarShow>
        <verticalScrollbarProgress>0</verticalScrollbarProgress>
        <horizontalScrollbarShow>False</horizontalScrollbarShow>
        <horizontalScrollbarProgress>0</horizontalScrollbarProgress>
        <links eventType="AtClick" animate="AmPushLeft" animateAutoDelay="0" animateDuration="500">
          <link targetPageID="" linkType="ltPageLink" isApplyIncludePage="False" title="%E9%93%BE%E6%8E%A5">
            <area shape="0" alt="" ID="{AB97645C-6E12-4508-B261-780F3510D6D0}" coords="(0,0,222,310)"/>
          </link>
        </links>
        <interactiveData>
          <entry title="">
            <area shape="0" alt="" ID="{8CE1E55E-6BA4-4AB4-9F2D-793E1DDFBD7B}" coords="(0,0,222,310)"/>
            <events title=""/>
          </entry>
        </interactiveData>
        <textSet textColor="4278190080" textSize="14" textFontFamily="%E5%BE%AE%E8%BD%AF%E9%9B%85%E9%BB%91" lineSpacingMultiple="1" textAlign="HaLeft" textVAlign="VaTop" textWordWrap="True" textStyles="[]" useDefaultTextSize="False">
          <text>1%E9%BB%91%E8%89%B2%E9%80%8F%E6%98%8E%E6%B5%AE%E5%B1%82%0D%0A-%E4%B8%8D%E5%8F%AF%E7%82%B9%E5%87%BB%0D%0A%0D%0A2%E5%BC%B9%E7%AA%97%E6%A0%87%E9%A2%98%0D%0A%0D%0A3%E5%BC%B9%E7%AA%97%E5%86%85%E5%AE%B9</text>
        </textSet>
        <selectedIndex>-1</selectedIndex>
        <selectedColor>4282501083</selectedColor>
        <textPadding>0</textPadding>
        <isShowTabBar>True</isShowTabBar>
      </controlProperties>
    </control>
    <control controlID="03EED16C-4452-4A70-B86F-6F712D689BC5" controlTypeID="StickyNote" isShow="True" caption="%E4%BE%BF%E7%AD%BE%E6%9D%A1" x="401" y="46" w="222" h="310" measuredW="109" measuredH="123" zOrder="10" locked="False" sizeLocked="False">
      <controlProperties>
        <basic color="4288243455" borderVisible="True" borderColor="4284900966" isAutoSize="False" status="MsEnabled" opacity="1" isCommentCom="True" canMove="True" alias="" rotation="0"/>
        <states/>
        <verticalScrollbarShow>False</verticalScrollbarShow>
        <verticalScrollbarProgress>0</verticalScrollbarProgress>
        <horizontalScrollbarShow>False</horizontalScrollbarShow>
        <horizontalScrollbarProgress>0</horizontalScrollbarProgress>
        <links eventType="AtClick" animate="AmPushLeft" animateAutoDelay="0" animateDuration="500">
          <link targetPageID="" linkType="ltPageLink" isApplyIncludePage="False" title="%E9%93%BE%E6%8E%A5">
            <area shape="0" alt="" ID="{AB97645C-6E12-4508-B261-780F3510D6D0}" coords="(0,0,222,310)"/>
          </link>
        </links>
        <interactiveData>
          <entry title="">
            <area shape="0" alt="" ID="{8CE1E55E-6BA4-4AB4-9F2D-793E1DDFBD7B}" coords="(0,0,222,310)"/>
            <events title=""/>
          </entry>
        </interactiveData>
        <textSet textColor="4294967295" textSize="14" textFontFamily="%E5%BE%AE%E8%BD%AF%E9%9B%85%E9%BB%91" lineSpacingMultiple="1" textAlign="HaLeft" textVAlign="VaTop" textWordWrap="True" textStyles="[]" useDefaultTextSize="False">
          <text>1%E5%8F%96%E6%B6%88%0D%0A-%E7%82%B9%E5%87%BB%E5%90%8E%E5%85%B3%E9%97%AD%E5%8D%8A%E9%80%8F%E6%98%8E%E6%B5%AE%E5%B1%82%E5%92%8C%E5%BC%B9%E7%AA%97%0D%0A-%E5%9B%9E%E5%88%B0%E8%81%8A%E5%A4%A9%E7%95%8C%E9%9D%A2%EF%BC%8C%E8%BE%93%E5%85%A5%E6%A1%86%E4%BE%9D%E7%84%B6%E4%B8%BA%E4%B8%8D%E5%8F%AF%E8%BE%93%E5%85%A5%E7%8A%B6%E6%80%81%EF%BC%8C%E7%82%B9%E5%87%BB%E5%90%8E%E5%86%8D%E6%AC%A1%E5%BC%B9%E5%87%BA%E7%A7%81%E8%81%8A%E5%B0%8F%E8%B4%B4%E5%A3%AB%0D%0A%0D%0A2%E9%87%8D%E6%96%B0%E6%94%AF%E4%BB%98%0D%0A-%E7%82%B9%E5%87%BB%E5%90%8E%E8%B7%B3%E8%BD%AC%E8%87%B3%5B7.1.1.4%5D%E6%94%AF%E4%BB%98%E9%A1%B5%E9%9D%A2</text>
        </textSet>
        <selectedIndex>-1</selectedIndex>
        <selectedColor>4282501083</selectedColor>
        <textPadding>0</textPadding>
        <isShowTabBar>True</isShowTabBar>
      </controlProperties>
    </control>
    <control controlID="0301C149-09B7-41CD-AA81-2B52365D105E" controlTypeID="Label" isShow="True" caption="%E5%8D%95%E8%A1%8C%E6%96%87%E5%AD%97" x="148" y="238" w="64" h="22" measuredW="0" measuredH="0" zOrder="11" locked="False" sizeLocked="False">
      <controlProperties>
        <basic color="0" borderVisible="True" borderColor="4284900966" isAutoSize="True" status="MsEnabled" opacity="1" isCommentCom="False" canMove="True" alias="" rotation="0"/>
        <states/>
        <verticalScrollbarShow>False</verticalScrollbarShow>
        <verticalScrollbarProgress>0</verticalScrollbarProgress>
        <horizontalScrollbarShow>False</horizontalScrollbarShow>
        <horizontalScrollbarProgress>0</horizontalScrollbarProgress>
        <links eventType="AtClick" animate="AmPushLeft" animateAutoDelay="0" animateDuration="500">
          <link targetPageID="" linkType="ltPageLink" isApplyIncludePage="False" title="%E9%93%BE%E6%8E%A5">
            <area shape="0" alt="" ID="{85DFE26F-57EF-43B2-842C-15AE029B9192}" coords="(0,0,64,22)"/>
          </link>
        </links>
        <interactiveData>
          <entry title="">
            <area shape="0" alt="" ID="{C9E593BF-83AD-4131-8A57-0512A5E7050C}" coords="(0,0,64,22)"/>
            <events title=""/>
          </entry>
        </interactiveData>
        <textSet textColor="4278190080" textSize="16" textFontFamily="%E5%BE%AE%E8%BD%AF%E9%9B%85%E9%BB%91" lineSpacingMultiple="1" textAlign="HaLeft" textVAlign="VaTop" textWordWrap="True" textStyles="[fsBold]" useDefaultTextSize="False">
          <text>%E6%94%AF%E4%BB%98%E5%A4%B1%E8%B4%A5</text>
        </textSet>
        <selectedIndex>-1</selectedIndex>
        <selectedColor>4282501083</selectedColor>
        <textPadding>0</textPadding>
      </controlProperties>
    </control>
  </controls>
  <param>
    <backgroundColor>4294967295</backgroundColor>
    <fontFamily>%E5%BE%AE%E8%BD%AF%E9%9B%85%E9%BB%91</fontFamily>
    <guideLines/>
  </param>
</mockup>